Metadata-Version: 2.1
Name: jesse-apexpro
Version: 1.0.0
Summary: Python3 Apexpro HTTP/WebSocket API Connector
Home-page: https://github.com/saleh-mir/apexpro-openapi
Author: Saleh Mir
Author-email: saleh@jesse.trade
License: MIT License
Keywords: apexpro api connector
Classifier: Development Status :: 4 - Beta
Classifier: Intended Audience :: Developers
Classifier: Topic :: Software Development :: Libraries :: Python Modules
Classifier: License :: OSI Approved :: MIT License
Classifier: Programming Language :: Python :: 3.8
Classifier: Programming Language :: Python :: 3.9
Classifier: Programming Language :: Python :: 3.10
Classifier: Programming Language :: Python :: 3.11
Requires-Python: >=3.8
License-File: LICENSE
Requires-Dist: requests
Requires-Dist: websocket-client
Requires-Dist: websockets
Requires-Dist: dateparser ==1.0.0
Requires-Dist: ecdsa ==0.16.0
Requires-Dist: eth-keys
Requires-Dist: eth-account <0.9.0,>=0.4.0
Requires-Dist: mpmath ==1.0.0
Requires-Dist: sympy ==1.6
Requires-Dist: tox
Requires-Dist: web3 ==6.10.0
